{
  "type": "Feature",
  "properties": {
    "iso:country":"KN",
    "name:bre_x_preferred":[
        "Middle Island"
    ],
    "name:deu_x_preferred":[
        "Middle Island"
    ],
    "name:eng_x_preferred":[
        "Middle Island"
    ],
    "name:mkd_x_preferred":[
        "\u041c\u0438\u0434\u043b \u0410\u0458\u043b\u0430\u043d\u0434"
    ],
    "name:nld_x_preferred":[
        "Middle Island"
    ],
    "name:pol_x_preferred":[
        "Middle Island"
    ],
    "name:spa_x_preferred":[
        "Middle Island"
    ],
    "name:swe_x_preferred":[
        "Middle Island"
    ],
    "name:unk_x_variant":[
        "Middle Island Village"
    ],
    "name:urd_x_preferred":[
        "\u0645\u0688\u0644 \u0622\u0626\u0644\u06cc\u0646\u0688\u060c \u0633\u06cc\u0646\u0679 \u06a9\u06cc\u0679\u0632 \u0648 \u0646\u0627\u0648\u06cc\u0633"
    ],
    "qs:gn_country":"KN",
    "qs:gn_fcode":"PPL",
    "qs:gn_pop":0,
    "qs:name":"Middle Island",
    "qs:name_adm0":"Saint Kitts and Nevis",
    "qs:name_adm1":"Saint Thomas Middle Island",
    "qs:photos":903,
    "qs:photos_1k":183,
    "qs:photos_9k":4,
    "qs:photos_9r":6,
    "qs:photos_all":903,
    "qs:photos_sr":10,
    "qs:placetype":"Town",
    "qs:pop_sr":"0",
    "qs:woe_adm0":23424940,
    "wof:name":"Middle Island",
    "wof:placetype":"locality"
},
  "geometry": {"coordinates":[-62.81667,17.31667],"type":"Point"}
}