{
  "type": "Feature",
  "properties": {
    "gn:admin1_code":"11.0",
    "gn:asciiname":"Ogee's",
    "gn:country_code":"KN",
    "gn:dem":1,
    "gn:feature_class":"P",
    "gn:feature_code":"PPL",
    "gn:name":"Ogee\u2019s",
    "gn:population":0,
    "gn:timezone":"America/St_Kitts",
    "iso:country":"KN",
    "name:und_x_variant":[
        "Ogees Village",
        "Ogee\u2019s"
    ],
    "wof:name":"Ogee's",
    "wof:placetype":"locality"
},
  "geometry": {"coordinates":[-62.73311999999999,17.33009],"type":"Point"}
}