{
  "type": "Feature",
  "properties": {
    "gn:admin1_code":"5.0",
    "gn:asciiname":"Whitehall",
    "gn:country_code":"KN",
    "gn:dem":1,
    "gn:feature_class":"P",
    "gn:feature_code":"PPL",
    "gn:name":"Whitehall",
    "gn:population":0,
    "gn:timezone":"America/St_Kitts",
    "iso:country":"KN",
    "wof:name":"Whitehall",
    "wof:placetype":"locality"
},
  "geometry": {"coordinates":[-62.55834,17.18055],"type":"Point"}
}