{
  "type": "Feature",
  "properties": {
    "gn:admin1_code":"5.0",
    "gn:asciiname":"Mount Lily",
    "gn:country_code":"KN",
    "gn:dem":1,
    "gn:feature_class":"P",
    "gn:feature_code":"PPL",
    "gn:name":"Mount Lily",
    "gn:population":0,
    "gn:timezone":"America/St_Kitts",
    "iso:country":"KN",
    "name:und_x_variant":[
        "Mount Lily Village",
        "Mount Lily"
    ],
    "wof:name":"Mount Lily",
    "wof:placetype":"locality"
},
  "geometry": {"coordinates":[-62.58434000000001,17.1863],"type":"Point"}
}