{
  "type": "Feature",
  "properties": {
    "iso:country":"KN",
    "name:unk_x_variant":[
        "Perry"
    ],
    "qs:gn_country":"KN",
    "qs:gn_fcode":"PPL",
    "qs:gn_pop":0,
    "qs:name":"Parrys",
    "qs:name_adm0":"Antigua and Barbuda",
    "qs:name_adm1":"Saint Peter",
    "qs:photos":197,
    "qs:photos_1k":40,
    "qs:photos_9k":1,
    "qs:photos_9r":4,
    "qs:photos_all":197,
    "qs:photos_sr":4,
    "qs:placetype":"Town",
    "qs:pop_sr":"0",
    "qs:woe_adm0":23424737,
    "wof:name":"Parrys",
    "wof:placetype":"locality"
},
  "geometry": {"coordinates":[-62.71667,17.31667],"type":"Point"}
}