{
  "type": "Feature",
  "properties": {
    "iso:country":"KN",
    "qs:gn_pop":0,
    "qs:name":"Stonyhill",
    "qs:name_adm0":"Saint Kitts and Nevis",
    "qs:name_adm1":"Saint George Gingerland",
    "qs:photos":475,
    "qs:photos_1k":96,
    "qs:photos_9k":2,
    "qs:photos_9r":5,
    "qs:photos_all":475,
    "qs:photos_sr":7,
    "qs:placetype":"Town",
    "qs:pop_sr":"0",
    "qs:woe_adm0":23424940,
    "wof:name":"Stonyhill",
    "wof:placetype":"locality"
},
  "geometry": {"coordinates":[-62.568236,17.140294],"type":"Point"}
}