{
  "type": "Feature",
  "properties": {
    "iso:country":"KN",
    "name:ara_x_preferred":[
        "\u0643\u0627\u064a\u0648\u0646"
    ],
    "name:ceb_x_preferred":[
        "Cayon"
    ],
    "name:deu_x_preferred":[
        "Cayon"
    ],
    "name:eng_x_preferred":[
        "Cayon"
    ],
    "name:fas_x_preferred":[
        "\u06a9\u0627\u06cc\u0648\u0646\u060c \u0633\u0646\u062a \u06a9\u06cc\u062a\u0633 \u0648 \u0646\u0648\u06cc\u0633"
    ],
    "name:fas_x_variant":[
        "\u06a9\u0627\u06cc\u0648\u0646"
    ],
    "name:fra_x_preferred":[
        "Cayon"
    ],
    "name:heb_x_preferred":[
        "\u05e7\u05d0\u05d9\u05d5\u05df"
    ],
    "name:jpn_x_preferred":[
        "\u30b1\u30a4\u30aa\u30f3"
    ],
    "name:lit_x_preferred":[
        "Kajonas"
    ],
    "name:mkd_x_preferred":[
        "\u041a\u0430\u0458\u043e\u043d"
    ],
    "name:nld_x_preferred":[
        "Cayon"
    ],
    "name:pol_x_preferred":[
        "Cayon"
    ],
    "name:por_x_preferred":[
        "Cayon"
    ],
    "name:spa_x_preferred":[
        "Cayon"
    ],
    "name:swe_x_preferred":[
        "Cayon"
    ],
    "name:urd_x_preferred":[
        "\u06a9\u0627\u06cc\u0648\u0646"
    ],
    "name:zho_x_preferred":[
        "\u5361\u6c38"
    ],
    "qs:gn_pop":0,
    "qs:name":"Cayon",
    "qs:name_adm0":"Saint Kitts and Nevis",
    "qs:name_adm1":"Saint Mary Cayon",
    "qs:photos":195,
    "qs:photos_1k":40,
    "qs:photos_9k":1,
    "qs:photos_9r":4,
    "qs:photos_all":195,
    "qs:photos_sr":4,
    "qs:placetype":"Town",
    "qs:pop_sr":"0",
    "qs:woe_adm0":23424940,
    "wd:wordcount":69,
    "wof:name":"Cayon",
    "wof:placetype":"locality"
},
  "geometry": {"coordinates":[-62.735366,17.349819],"type":"Point"}
}