{
  "type": "Feature",
  "properties": {
    "gn:admin1_code":"6.0",
    "gn:asciiname":"Harris",
    "gn:country_code":"KN",
    "gn:dem":29,
    "gn:feature_class":"P",
    "gn:feature_code":"PPL",
    "gn:name":"Harris",
    "gn:population":0,
    "gn:timezone":"America/St_Kitts",
    "iso:country":"KN",
    "wof:name":"Harris",
    "wof:placetype":"locality"
},
  "geometry": {"coordinates":[-62.78746999999999,17.40275],"type":"Point"}
}