{
  "type": "Feature",
  "properties": {
    "gn:admin1_code":"4.0",
    "gn:asciiname":"Crook's Ground",
    "gn:country_code":"KN",
    "gn:dem":1,
    "gn:feature_class":"P",
    "gn:feature_code":"PPL",
    "gn:name":"Crook\u2019s Ground",
    "gn:population":0,
    "gn:timezone":"America/St_Kitts",
    "iso:country":"KN",
    "wof:name":"Crook's Ground",
    "wof:placetype":"locality"
},
  "geometry": {"coordinates":[-62.56793,17.12875],"type":"Point"}
}