{
  "type": "Feature",
  "properties": {
    "gn:admin1_code":"5.0",
    "gn:asciiname":"Fountain",
    "gn:country_code":"KN",
    "gn:dem":1,
    "gn:feature_class":"P",
    "gn:feature_code":"PPL",
    "gn:name":"Fountain",
    "gn:population":0,
    "gn:timezone":"America/St_Kitts",
    "iso:country":"KN",
    "name:und_x_variant":[
        "Fountain Village",
        "Fountain"
    ],
    "wof:name":"Fountain",
    "wof:placetype":"locality"
},
  "geometry": {"coordinates":[-62.59155,17.18126],"type":"Point"}
}