{
  "type": "Feature",
  "properties": {
    "gn:admin1_code":"11.0",
    "gn:asciiname":"Douglas",
    "gn:country_code":"KN",
    "gn:dem":72,
    "gn:feature_class":"P",
    "gn:feature_code":"PPL",
    "gn:name":"Douglas",
    "gn:population":0,
    "gn:timezone":"America/St_Kitts",
    "iso:country":"KN",
    "name:afr_x_preferred":[
        "Douglas"
    ],
    "name:bul_x_preferred":[
        "\u0414\u044a\u0433\u043b\u0430\u0441"
    ],
    "name:cat_x_preferred":[
        "Douglas"
    ],
    "name:ceb_x_preferred":[
        "Douglas"
    ],
    "name:ces_x_preferred":[
        "Douglas"
    ],
    "name:cym_x_preferred":[
        "Douglas"
    ],
    "name:dan_x_preferred":[
        "Douglas"
    ],
    "name:deu_x_preferred":[
        "Douglas"
    ],
    "name:epo_x_preferred":[
        "Douglas"
    ],
    "name:fas_x_preferred":[
        "\u062f\u0627\u06af\u0644\u0627\u0633"
    ],
    "name:fin_x_preferred":[
        "Douglas"
    ],
    "name:fra_x_preferred":[
        "Douglas"
    ],
    "name:fry_x_preferred":[
        "Douglas"
    ],
    "name:glg_x_preferred":[
        "Douglas"
    ],
    "name:heb_x_preferred":[
        "\u05d3\u05d0\u05d2\u05dc\u05e1"
    ],
    "name:ita_x_preferred":[
        "Douglas"
    ],
    "name:jpn_x_preferred":[
        "\u30c0\u30b0\u30e9\u30b9"
    ],
    "name:kor_x_preferred":[
        "\ub354\uae00\ub77c\uc2a4"
    ],
    "name:kor_x_variant":[
        "\ub354\uae00\ub7ec\uc2a4"
    ],
    "name:nds_x_preferred":[
        "Douglas"
    ],
    "name:nld_x_preferred":[
        "Douglas"
    ],
    "name:nor_x_preferred":[
        "Douglas"
    ],
    "name:pol_x_preferred":[
        "Douglas"
    ],
    "name:por_x_preferred":[
        "Douglas"
    ],
    "name:ron_x_preferred":[
        "Douglas"
    ],
    "name:rus_x_preferred":[
        "\u0414\u0443\u0433\u043b\u0430\u0441"
    ],
    "name:rus_x_variant":[
        "Douglas"
    ],
    "name:sco_x_preferred":[
        "Douglas"
    ],
    "name:slk_x_preferred":[
        "Douglas"
    ],
    "name:slv_x_preferred":[
        "Douglas"
    ],
    "name:spa_x_preferred":[
        "Douglas"
    ],
    "name:srp_x_preferred":[
        "\u0414\u0430\u0433\u043b\u0430\u0441"
    ],
    "name:swe_x_preferred":[
        "Douglas"
    ],
    "name:tur_x_preferred":[
        "Douglas"
    ],
    "name:ukr_x_preferred":[
        "\u0414\u0430\u0433\u043b\u0430\u0441"
    ],
    "name:urd_x_preferred":[
        "\u0688\u06af\u0644\u0633"
    ],
    "name:vie_x_preferred":[
        "Douglas"
    ],
    "name:vol_x_preferred":[
        "Douglas"
    ],
    "name:war_x_preferred":[
        "Douglas"
    ],
    "name:zho_x_preferred":[
        "\u9053\u683c\u62c9\u65af"
    ],
    "wof:name":"Douglas",
    "wof:placetype":"locality"
},
  "geometry": {"coordinates":[-62.71667,17.31667],"type":"Point"}
}