{
  "type": "Feature",
  "properties": {
    "gn:country":"KN",
    "gn:fcode":"PPL",
    "gn:pop":493,
    "iso:country":"KN",
    "qs:name":"Gingerland",
    "qs:photos_9r":0,
    "qs:photos_sr":0,
    "qs:pop_sr":"2",
    "wof:name":"Gingerland",
    "wof:placetype":"locality",
    "wof:population":493
},
  "geometry": {"coordinates":[-62.55,17.13333],"type":"Point"}
}