{
  "type": "Feature",
  "properties": {
    "gn:admin1_code":"4.0",
    "gn:asciiname":"New River",
    "gn:country_code":"KN",
    "gn:dem":1,
    "gn:feature_class":"P",
    "gn:feature_code":"PPL",
    "gn:name":"New River",
    "gn:population":0,
    "gn:timezone":"America/St_Kitts",
    "iso:country":"KN",
    "wof:name":"New River",
    "wof:placetype":"locality"
},
  "geometry": {"coordinates":[-62.55266,17.14526],"type":"Point"}
}