{
  "type": "Feature",
  "properties": {
    "gn:admin1_code":"4.0",
    "gn:asciiname":"New River",
    "gn:country_code":"KN",
    "gn:dem":1,
    "gn:feature_class":"P",
    "gn:feature_code":"PPL",
    "gn:name":"New River",
    "gn:population":0,
    "gn:timezone":"America/St_Kitts",
    "iso:country":"KN",
    "name:ceb_x_preferred":[
        "New River"
    ],
    "name:chv_x_preferred":[
        "\u041d\u044c\u044e-\u0420\u0438\u0432\u0435\u0440"
    ],
    "name:deu_x_preferred":[
        "New River"
    ],
    "name:fra_x_preferred":[
        "New River"
    ],
    "name:nds_x_preferred":[
        "New River"
    ],
    "name:pol_x_preferred":[
        "New River"
    ],
    "name:rus_x_preferred":[
        "\u041d\u044c\u044e-\u0420\u0438\u0432\u0435\u0440"
    ],
    "name:srp_x_preferred":[
        "\u040a\u0443 \u0420\u0438\u0432\u0435\u0440"
    ],
    "name:swe_x_preferred":[
        "New River"
    ],
    "name:ukr_x_preferred":[
        "\u041d\u044c\u044e-\u0420\u0456\u0432\u0435\u0440"
    ],
    "wof:name":"New River",
    "wof:placetype":"locality"
},
  "geometry": {"coordinates":[-62.55266,17.14526],"type":"Point"}
}