{
  "type": "Feature",
  "properties": {
    "gn:admin1_code":"5.0",
    "gn:asciiname":"Brick Kiln",
    "gn:cc2":"KN",
    "gn:country_code":"KN",
    "gn:dem":78,
    "gn:feature_class":"P",
    "gn:feature_code":"PPL",
    "gn:name":"Brick Kiln",
    "gn:population":0,
    "gn:timezone":"America/St_Kitts",
    "iso:country":"KN",
    "name:hin_x_preferred":[
        "\u0908\u0902\u091f \u0915\u093e \u092d\u091f\u094d\u0920\u093e"
    ],
    "name:und_x_variant":[
        "Brick Kiln Village",
        "Brick Kiln"
    ],
    "wof:name":"Brick Kiln",
    "wof:placetype":"locality"
},
  "geometry": {"coordinates":[-62.55345,17.17532000000001],"type":"Point"}
}